kyc/__init__.py
kyc/api_config.py
kyc/connection.py
kyc/get.py
kyc/get_company.py
kyc/get_group.py
kyc/message.py
kyc/search_company.py
kyc/search_director.py
kyc/search_group.py
kyc/util.py
kyc/version.py
kyc/errors/__init__.py
kyc/errors/tej_error.py
kyc/model/__init__.py
kyc/model/data.py
kyc/model/data_list.py
kyc/model/data_mixin.py
kyc/model/database.py
kyc/model/datatable.py
kyc/model/merged_data_list.py
kyc/model/model_base.py
kyc/model/model_list.py
kyc/model/paginated_list.py
kyc/operations/__init__.py
kyc/operations/data_list.py
kyc/operations/get.py
kyc/operations/list.py
kyc/operations/operation.py
kyc/utils/__init__.py
kyc/utils/api_key_util.py
kyc-0.1.2.dist-info/METADATA
kyc-0.1.2.dist-info/WHEEL
kyc-0.1.2.dist-info/top_level.txt
kyc-0.1.2.dist-info/RECORD
